huawei_solar/__init__.py
huawei_solar/bridge.py
huawei_solar/const.py
huawei_solar/exceptions.py
huawei_solar/files.py
huawei_solar/huawei_solar.py
huawei_solar/modbus.py
huawei_solar/py.typed
huawei_solar/register_names.py
huawei_solar/register_values.py
huawei_solar/registers.py
huawei_solar/utils.py
huawei_solar-2.4.7.dist-info/METADATA
huawei_solar-2.4.7.dist-info/WHEEL
huawei_solar-2.4.7.dist-info/licenses/LICENSE.md
huawei_solar-2.4.7.dist-info/RECORD
