Metadata-Version: 2.4
Name: huawei-solar
Version: 2.4.7
Summary: A Python wrapper for the Huawei Inverter modbus TCP API
Project-URL: Homepage, https://gitlab.com/EmilV2/huawei-solar
Author: Thijs Walcarius
Author-email: Emil Vanherp <emil@vanherp.me>
License:                     GNU AFFERO GENERAL PUBLIC LICENSE
License-File: LICENSE.md
Keywords: battery,huawei,inverter,modbus,modbus-rtu,modbus-tcp,solar,sun2000
Classifier: Development Status :: 5 - Production/Stable
Classifier: License :: OSI Approved :: GNU Affero General Public License v3
Classifier: Operating System :: OS Independent
Classifier: Programming Language :: Python :: 3.10
Classifier: Programming Language :: Python :: 3.11
Classifier: Programming Language :: Python :: 3.12
Classifier: Topic :: Home Automation
Requires-Python: >=3.11
Requires-Dist: backoff
Requires-Dist: pymodbus<4,>=3.11.0
Requires-Dist: pyserial-asyncio>=0.6
Requires-Dist: pytz
